LICENSE
MANIFEST.in
README.md
requirements.txt
setup.cfg
setup.py
mysocks/Test_Server.py
mysocks/__init__.py
mysocks/chat.py
mysocks/file_send.py
mysocks/file_transfer.py
mysocks/utilities.py
mysocks.egg-info/PKG-INFO
mysocks.egg-info/SOURCES.txt
mysocks.egg-info/dependency_links.txt
mysocks.egg-info/requires.txt
mysocks.egg-info/top_level.txt