Metadata-Version: 2.1
Name: mysocks
Version: 1.0.3
Summary: Testing installation of sockets package
Home-page: https://github.com/Mahanotrahul/mysocks
Author: Rahul Mahanot
Author-email: thecodeboxed@gmail.com
License: MIT
Download-URL: https://github.com/Mahanotrahul/mysocks/archive/1.0.2.tar.gz
Platform: UNKNOWN
